main.py
mseep_qgis_mcp-0.1.5.dist-info/licenses/LICENSE
mseep_qgis_mcp-0.1.5.dist-info/METADATA
mseep_qgis_mcp-0.1.5.dist-info/WHEEL
mseep_qgis_mcp-0.1.5.dist-info/entry_points.txt
mseep_qgis_mcp-0.1.5.dist-info/top_level.txt
mseep_qgis_mcp-0.1.5.dist-info/RECORD
