Metadata-Version: 2.4
Name: mseep-qgis-mcp
Version: 0.1.5
Summary: Add your description here
Author-email: mseep <support@skydeck.ai>
Requires-Python: >=3.12
License-File: LICENSE
Requires-Dist: mcp[cli]>=1.3.0
Dynamic: license-file
